py_authorization/__init__.py
py_authorization/authorization.py
py_authorization/context.py
py_authorization/policy.py
py_authorization/policy_strategy.py
py_authorization/policy_strategy_builder.py
py_authorization/py.typed
py_authorization/sql_parser.py
py_authorization/user.py
py_authorization-1.6.1.dist-info/LICENSE
py_authorization-1.6.1.dist-info/WHEEL
py_authorization-1.6.1.dist-info/METADATA
py_authorization-1.6.1.dist-info/RECORD
