Metadata-Version: 2.1
Name: py_authorization
Version: 1.6.1
Summary: Easily manage authorization complex logic
Requires-Python: >=3.7
Requires-Dist: SQLAlchemy>=1.4,<3.0
